alidaassets/__init__.py
alidaassets/dataset.py
alidaassets/model.py
alidaassets/utils.py
alidaassets/serializations/__init__.py
alidaassets/serializations/_pandas_core_frame_dataframe.py
alidaassets/serializations/hugging_face_dataset.py
alidaassets/serializations/hugging_face_from_csv.py
alidaassets/serializations/kafka_channel.py
alidaassets/serializations/pandas_dataframe.py
alidaassets/serializations/path.py
alidaassets/serializations/streaming_input.py
alidaassets/serializations/streaming_output.py
alida_assets-0.0.2.dist-info/METADATA
alida_assets-0.0.2.dist-info/WHEEL
alida_assets-0.0.2.dist-info/top_level.txt
alida_assets-0.0.2.dist-info/RECORD
